package_anushka/__init__.py
package_anushka/api_dealer.py
package_anushka-0.1.dist-info/METADATA
package_anushka-0.1.dist-info/WHEEL
package_anushka-0.1.dist-info/top_level.txt
package_anushka-0.1.dist-info/RECORD
